yuntools/__init__.py
yuntools/lib2.py
yuntools-0.1.dist-info/METADATA
yuntools-0.1.dist-info/WHEEL
yuntools-0.1.dist-info/top_level.txt
yuntools-0.1.dist-info/RECORD
